README.txt
setup.py
pyf/__init__.py
pyf.manager.egg-info/PKG-INFO
pyf.manager.egg-info/SOURCES.txt
pyf.manager.egg-info/dependency_links.txt
pyf.manager.egg-info/entry_points.txt
pyf.manager.egg-info/namespace_packages.txt
pyf.manager.egg-info/not-zip-safe
pyf.manager.egg-info/requires.txt
pyf.manager.egg-info/top_level.txt
pyf/manager/__init__.py
pyf/manager/main.py
pyf/manager/network.py
pyf/manager/path.py