Metadata-Version: 1.0
Name: pyf.manager
Version: 2.0
Summary: DataFlow management system (network and path system) for PyF
Home-page: http://pyfproject.org
Author: UNKNOWN
Author-email: UNKNOWN
License: MIT
Platform: UNKNOWN
Classifier: Programming Language :: Python
